mdc_ds/__init__.py
mdc_ds/cached_datasets.json
mdc_ds/client/__init__.py
mdc_ds/client/_client.py
mdc_ds/registry.py
mdc_ds/types/__init__.py
mdc_ds/types/dataset_details.py
mdc_ds/types/download_session.py
mdc_ds/types/orgnazation.py
mdc_ds/utils/__init__.py
mdc_ds/utils/ensure_output.py
mdc_ds/utils/unpack_archive.py
mdc_ds-0.2.0.dist-info/METADATA
mdc_ds-0.2.0.dist-info/WHEEL
mdc_ds-0.2.0.dist-info/licenses/LICENSE
mdc_ds-0.2.0.dist-info/RECORD
