Metadata-Version: 2.4
Name: mdc-ds
Version: 0.2.0
Summary: Mozilla Data Collective API client with some utilities.
License: MIT
License-File: LICENSE
Author: Allen Chou
Author-email: f1470891079@gmail.com
Requires-Python: >=3.11,<4
Classifier: License :: OSI Approved :: MIT License
Classifier: Programming Language :: Python :: 3
Classifier: Programming Language :: Python :: 3.11
Classifier: Programming Language :: Python :: 3.12
Classifier: Programming Language :: Python :: 3.13
Classifier: Programming Language :: Python :: 3.14
Requires-Dist: aiofiles
Requires-Dist: httpx
Requires-Dist: pydantic (>=2)
Requires-Dist: pydantic-settings
Requires-Dist: str-or-none
Project-URL: Homepage, https://github.com/allen2c/mdc-ds
Project-URL: PyPI, https://pypi.org/project/mdc-ds/
Project-URL: Repository, https://github.com/allen2c/mdc-ds
